ninja/__init__.py
ninja/conf.py
ninja/constants.py
ninja/decorators.py
ninja/errors.py
ninja/files.py
ninja/filter_schema.py
ninja/main.py
ninja/operation.py
ninja/pagination.py
ninja/parser.py
ninja/patch_dict.py
ninja/py.typed
ninja/renderers.py
ninja/responses.py
ninja/router.py
ninja/schema.py
ninja/throttling.py
ninja/types.py
ninja/utils.py
ninja/compatibility/__init__.py
ninja/compatibility/files.py
ninja/compatibility/util.py
ninja/management/__init__.py
ninja/management/utils.py
ninja/management/commands/__init__.py
ninja/management/commands/export_openapi_schema.py
ninja/openapi/__init__.py
ninja/openapi/docs.py
ninja/openapi/schema.py
ninja/openapi/urls.py
ninja/openapi/views.py
ninja/orm/__init__.py
ninja/orm/factory.py
ninja/orm/fields.py
ninja/orm/metaclass.py
ninja/orm/shortcuts.py
ninja/params/__init__.py
ninja/params/functions.py
ninja/params/models.py
ninja/security/__init__.py
ninja/security/apikey.py
ninja/security/base.py
ninja/security/http.py
ninja/security/session.py
ninja/signature/__init__.py
ninja/signature/details.py
ninja/signature/utils.py
ninja/static/ninja/favicon.png
ninja/static/ninja/redoc.standalone.js
ninja/static/ninja/redoc.standalone.js.map
ninja/static/ninja/swagger-ui-bundle.js
ninja/static/ninja/swagger-ui-bundle.js.map
ninja/static/ninja/swagger-ui-init.js
ninja/static/ninja/swagger-ui.css
ninja/static/ninja/swagger-ui.css.map
ninja/templates/ninja/redoc.html
ninja/templates/ninja/redoc_cdn.html
ninja/templates/ninja/swagger.html
ninja/templates/ninja/swagger_cdn.html
ninja/testing/__init__.py
ninja/testing/client.py
django_ninja-1.4.4.dist-info/licenses/LICENSE
django_ninja-1.4.4.dist-info/WHEEL
django_ninja-1.4.4.dist-info/METADATA
django_ninja-1.4.4.dist-info/RECORD
